lil_pwny/__init__.py
lil_pwny/__main__.py
lil_pwny/exceptions.py
lil_pwny/hashing.py
lil_pwny/loggers.py
lil_pwny/password_audit.py
lil_pwny/variant_generators/__init__.py
lil_pwny/variant_generators/custom_variant_generator.py
lil_pwny/variant_generators/username_variant_generator.py
lil_pwny-3.2.0.dist-info/LICENSE
lil_pwny-3.2.0.dist-info/METADATA
lil_pwny-3.2.0.dist-info/WHEEL
lil_pwny-3.2.0.dist-info/entry_points.txt
lil_pwny-3.2.0.dist-info/RECORD
