Metadata-Version: 2.1
Name: lil-pwny
Version: 3.2.0
Summary: Fast offline auditing of Active Directory passwords using Python and multiprocessing
License: GPL-3.0
Author: PaperMtn
Author-email: papermtn@protonmail.com
Requires-Python: >=3.11
Classifier: License :: OSI Approved :: GNU General Public License v3 (GPLv3)
Classifier: Programming Language :: Python :: 3
Classifier: Programming Language :: Python :: 3.11
Classifier: Programming Language :: Python :: 3.12
Requires-Dist: charset-normalizer (>=3.3.2,<4.0.0)
Requires-Dist: colorama (>=0.4.6,<0.5.0)
Requires-Dist: pycryptodome (>=3.20.0,<4.0.0)
